bigplanet/__init__.py
bigplanet/archive.py
bigplanet/bigplanet.py
bigplanet/bigplanet_version.py
bigplanet/bpstatus.py
bigplanet/extract.py
bigplanet/filter.py
bigplanet/process.py
bigplanet/read.py
bigplanet-3.0.1.dist-info/LICENSE
bigplanet-3.0.1.dist-info/METADATA
bigplanet-3.0.1.dist-info/WHEEL
bigplanet-3.0.1.dist-info/entry_points.txt
bigplanet-3.0.1.dist-info/top_level.txt
bigplanet-3.0.1.dist-info/RECORD
