Metadata-Version: 2.1
Name: bigplanet
Version: 3.0.1
Summary: VPLANET Data Analysis Tools
Home-page: https://github.com/VirtualPlanetaryLaboratory/BigPlanet
Author: Caitlyn Wilhelm
Author-email: cwilhelm@uw.edu
License: MIT
License-File: LICENSE
Requires-Dist: numpy
Requires-Dist: h5py
Requires-Dist: argparse
Requires-Dist: scipy
Requires-Dist: pandas
